stnavbar/Navbar.py
stnavbar/__init__.py
stnavbar-0.0.20.dist-info/METADATA
stnavbar-0.0.20.dist-info/WHEEL
stnavbar-0.0.20.dist-info/top_level.txt
stnavbar-0.0.20.dist-info/RECORD
