Metadata-Version: 2.1
Name: stnavbar
Version: 0.0.20
Summary: A navbar for streamlit
Author: BugzTheBunny
Author-email: 
License: UNKNOWN
Keywords: streamlit_nav,streamlit navbar,navbar,streamlit
Platform: UNKNOWN
Classifier: Intended Audience :: Developers
Classifier: Programming Language :: Python :: 3
Classifier: Operating System :: Unix
Classifier: Operating System :: MacOS :: MacOS X
Classifier: Operating System :: Microsoft :: Windows
Requires-Dist: streamlit
